vitis_quantizer/BUILD
vitis_quantizer/__init__.py
vitis_quantizer/vitis_quantize.py
vitis_quantizer/vitis_quantize_strategies.py
vitis_quantizer/__pycache__/__init__.cpython-38.pyc
vitis_quantizer/__pycache__/vitis_quantize.cpython-38.pyc
vitis_quantizer/__pycache__/vitis_quantize_strategies.cpython-38.pyc
vitis_quantizer/base/BUILD
vitis_quantizer/base/__init__.py
vitis_quantizer/base/quantize_annotate.py
vitis_quantizer/base/quantize_config.py
vitis_quantizer/base/quantize_registry.py
vitis_quantizer/base/quantize_strategy.py
vitis_quantizer/base/quantizer.py
vitis_quantizer/base/__pycache__/__init__.cpython-38.pyc
vitis_quantizer/base/__pycache__/quantize_annotate.cpython-38.pyc
vitis_quantizer/base/__pycache__/quantize_config.cpython-38.pyc
vitis_quantizer/base/__pycache__/quantize_registry.cpython-38.pyc
vitis_quantizer/base/__pycache__/quantize_strategy.cpython-38.pyc
vitis_quantizer/base/__pycache__/quantizer.cpython-38.pyc
vitis_quantizer/common/BUILD
vitis_quantizer/common/__init__.py
vitis_quantizer/common/vitis_quantize_aware_activation.py
vitis_quantizer/common/vitis_quantize_configs.py
vitis_quantizer/common/vitis_quantize_ops.py
vitis_quantizer/common/vitis_quantize_registry.py
vitis_quantizer/common/vitis_quantize_strategy.py
vitis_quantizer/common/vitis_quantize_wrapper.py
vitis_quantizer/common/vitis_quantizers.py
vitis_quantizer/common/__pycache__/__init__.cpython-38.pyc
vitis_quantizer/common/__pycache__/vitis_quantize_aware_activation.cpython-38.pyc
vitis_quantizer/common/__pycache__/vitis_quantize_configs.cpython-38.pyc
vitis_quantizer/common/__pycache__/vitis_quantize_ops.cpython-38.pyc
vitis_quantizer/common/__pycache__/vitis_quantize_registry.cpython-38.pyc
vitis_quantizer/common/__pycache__/vitis_quantize_strategy.cpython-38.pyc
vitis_quantizer/common/__pycache__/vitis_quantize_wrapper.cpython-38.pyc
vitis_quantizer/common/__pycache__/vitis_quantizers.cpython-38.pyc
vitis_quantizer/eight_bit/BUILD
vitis_quantizer/eight_bit/__init__.py
vitis_quantizer/vitis_quantizer.egg-info/PKG-INFO
vitis_quantizer/vitis_quantizer.egg-info/SOURCES.txt
vitis_quantizer/vitis_quantizer.egg-info/dependency_links.txt
vitis_quantizer/vitis_quantizer.egg-info/requires.txt
vitis_quantizer/vitis_quantizer.egg-info/top_level.txt
vitis_quantizer-0.1.0.dist-info/LICENSE
vitis_quantizer-0.1.0.dist-info/METADATA
vitis_quantizer-0.1.0.dist-info/WHEEL
vitis_quantizer-0.1.0.dist-info/top_level.txt
vitis_quantizer-0.1.0.dist-info/RECORD
